{
 "name": "RPlog_SW1_Log_2000-06-03",
 "title": "Brawl in Fountain Square",
 "summary": "In Plaxton City's Fountain Square on Caspar, the enraged Caspian Sar Admiral Salonika Batrad pins the IGNews reporter Loy Marin to the ground, demanding the source behind a published story alleging that the New Republic general Arands fathered Batrad's child. Batrad's wife Nicole and the marine Captain Ernie Pallando look on as the confrontation escalates, drawing a tense crowd, armed Caspian marines, and New Republic Intelligence agents led by Jonau Diggs. Arands intervenes, surrendering his sidearm and vowing to stop the beating by force if necessary, while the disguised agent Bazil McKenzie and his teammate Marcus watch warily from a bench. As marines from Trinum Base flood the square, the standoff cools: Arands storms off, Batrad shoves the reporter down and departs, and the FLS executive Benjawa smoothly steps in to help the shaken Loy to his feet and offer him sanctuary, with both men sensing future advantage in the encounter.",
 "rows": [
  {
   "line": 17,
   "type": "scene",
   "actor": "",
   "b": false
  },
  {
   "line": 19,
   "type": "desc",
   "actor": "Nicole Brouillard-Batrad",
   "b": false
  },
  {
   "line": 20,
   "type": "desc",
   "actor": "Nicole Brouillard-Batrad",
   "b": false
  },
  {
   "line": 21,
   "type": "desc",
   "actor": "Nicole Brouillard-Batrad",
   "b": false
  },
  {
   "line": 22,
   "type": "desc",
   "actor": "Nicole Brouillard-Batrad",
   "b": false
  },
  {
   "line": 23,
   "type": "desc",
   "actor": "Nicole Brouillard-Batrad",
   "b": false
  },
  {
   "line": 24,
   "type": "desc",
   "actor": "Nicole Brouillard-Batrad",
   "b": false
  },
  {
   "line": 25,
   "type": "desc",
   "actor": "Nicole Brouillard-Batrad",
   "b": false
  },
  {
   "line": 26,
   "type": "desc",
   "actor": "Nicole Brouillard-Batrad",
   "b": false
  },
  {
   "line": 27,
   "type": "desc",
   "actor": "Nicole Brouillard-Batrad",
   "b": false
  },
  {
   "line": 28,
   "type": "desc",
   "actor": "Nicole Brouillard-Batrad",
   "b": false
  },
  {
   "line": 29,
   "type": "desc",
   "actor": "Nicole Brouillard-Batrad",
   "b": false
  },
  {
   "line": 30,
   "type": "desc",
   "actor": "Nicole Brouillard-Batrad",
   "b": false
  },
  {
   "line": 31,
   "type": "desc",
   "actor": "Nicole Brouillard-Batrad",
   "b": false
  },
  {
   "line": 32,
   "type": "desc",
   "actor": "Nicole Brouillard-Batrad",
   "b": false
  },
  {
   "line": 33,
   "type": "desc",
   "actor": "Nicole Brouillard-Batrad",
   "b": false
  },
  {
   "line": 34,
   "type": "desc",
   "actor": "Nicole Brouillard-Batrad",
   "b": false
  },
  {
   "line": 35,
   "type": "desc",
   "actor": "Nicole Brouillard-Batrad",
   "b": false
  },
  {
   "line": 36,
   "type": "desc",
   "actor": "Nicole Brouillard-Batrad",
   "b": false
  },
  {
   "line": 37,
   "type": "desc",
   "actor": "Nicole Brouillard-Batrad",
   "b": false
  },
  {
   "line": 38,
   "type": "desc",
   "actor": "Nicole Brouillard-Batrad",
   "b": false
  },
  {
   "line": 39,
   "type": "desc",
   "actor": "Nicole Brouillard-Batrad",
   "b": false
  },
  {
   "line": 40,
   "type": "desc",
   "actor": "Nicole Brouillard-Batrad",
   "b": false
  },
  {
   "line": 42,
   "type": "desc",
   "actor": "Ernie Pallando",
   "b": false
  },
  {
   "line": 43,
   "type": "desc",
   "actor": "Ernie Pallando",
   "b": false
  },
  {
   "line": 44,
   "type": "desc",
   "actor": "Ernie Pallando",
   "b": false
  },
  {
   "line": 45,
   "type": "desc",
   "actor": "Ernie Pallando",
   "b": false
  },
  {
   "line": 46,
   "type": "desc",
   "actor": "Ernie Pallando",
   "b": false
  },
  {
   "line": 47,
   "type": "desc",
   "actor": "Ernie Pallando",
   "b": false
  },
  {
   "line": 48,
   "type": "desc",
   "actor": "Ernie Pallando",
   "b": false
  },
  {
   "line": 49,
   "type": "desc",
   "actor": "Ernie Pallando",
   "b": false
  },
  {
   "line": 50,
   "type": "desc",
   "actor": "Ernie Pallando",
   "b": false
  },
  {
   "line": 51,
   "type": "desc",
   "actor": "Ernie Pallando",
   "b": false
  },
  {
   "line": 52,
   "type": "desc",
   "actor": "Ernie Pallando",
   "b": false
  },
  {
   "line": 53,
   "type": "desc",
   "actor": "Ernie Pallando",
   "b": false
  },
  {
   "line": 54,
   "type": "desc",
   "actor": "Ernie Pallando",
   "b": false
  },
  {
   "line": 55,
   "type": "desc",
   "actor": "Ernie Pallando",
   "b": false
  },
  {
   "line": 56,
   "type": "desc",
   "actor": "Ernie Pallando",
   "b": false
  },
  {
   "line": 57,
   "type": "desc",
   "actor": "Ernie Pallando",
   "b": false
  },
  {
   "line": 58,
   "type": "desc",
   "actor": "Ernie Pallando",
   "b": false
  },
  {
   "line": 59,
   "type": "desc",
   "actor": "Ernie Pallando",
   "b": false
  },
  {
   "line": 60,
   "type": "desc",
   "actor": "Ernie Pallando",
   "b": false
  },
  {
   "line": 61,
   "type": "desc",
   "actor": "Ernie Pallando",
   "b": false
  },
  {
   "line": 63,
   "type": "desc",
   "actor": "Loy Marin",
   "b": false
  },
  {
   "line": 64,
   "type": "desc",
   "actor": "Loy Marin",
   "b": false
  },
  {
   "line": 65,
   "type": "desc",
   "actor": "Loy Marin",
   "b": false
  },
  {
   "line": 66,
   "type": "desc",
   "actor": "Loy Marin",
   "b": false
  },
  {
   "line": 67,
   "type": "desc",
   "actor": "Loy Marin",
   "b": false
  },
  {
   "line": 68,
   "type": "desc",
   "actor": "Loy Marin",
   "b": false
  },
  {
   "line": 69,
   "type": "desc",
   "actor": "Loy Marin",
   "b": false
  },
  {
   "line": 70,
   "type": "desc",
   "actor": "Loy Marin",
   "b": false
  },
  {
   "line": 71,
   "type": "desc",
   "actor": "Loy Marin",
   "b": false
  },
  {
   "line": 72,
   "type": "desc",
   "actor": "Loy Marin",
   "b": false
  },
  {
   "line": 73,
   "type": "desc",
   "actor": "Loy Marin",
   "b": false
  },
  {
   "line": 74,
   "type": "desc",
   "actor": "Loy Marin",
   "b": false
  },
  {
   "line": 75,
   "type": "desc",
   "actor": "Loy Marin",
   "b": false
  },
  {
   "line": 76,
   "type": "desc",
   "actor": "Loy Marin",
   "b": false
  },
  {
   "line": 77,
   "type": "desc",
   "actor": "Loy Marin",
   "b": false
  },
  {
   "line": 78,
   "type": "desc",
   "actor": "Loy Marin",
   "b": false
  },
  {
   "line": 79,
   "type": "desc",
   "actor": "Loy Marin",
   "b": false
  },
  {
   "line": 80,
   "type": "desc",
   "actor": "Loy Marin",
   "b": false
  },
  {
   "line": 81,
   "type": "desc",
   "actor": "Loy Marin",
   "b": false
  },
  {
   "line": 83,
   "type": "desc",
   "actor": "Salonika Batrad",
   "b": false
  },
  {
   "line": 84,
   "type": "desc",
   "actor": "Salonika Batrad",
   "b": false
  },
  {
   "line": 85,
   "type": "desc",
   "actor": "Salonika Batrad",
   "b": false
  },
  {
   "line": 86,
   "type": "desc",
   "actor": "Salonika Batrad",
   "b": false
  },
  {
   "line": 87,
   "type": "desc",
   "actor": "Salonika Batrad",
   "b": false
  },
  {
   "line": 88,
   "type": "desc",
   "actor": "Salonika Batrad",
   "b": false
  },
  {
   "line": 89,
   "type": "desc",
   "actor": "Salonika Batrad",
   "b": false
  },
  {
   "line": 90,
   "type": "desc",
   "actor": "Salonika Batrad",
   "b": false
  },
  {
   "line": 91,
   "type": "desc",
   "actor": "Salonika Batrad",
   "b": false
  },
  {
   "line": 92,
   "type": "desc",
   "actor": "Salonika Batrad",
   "b": false
  },
  {
   "line": 93,
   "type": "desc",
   "actor": "Salonika Batrad",
   "b": false
  },
  {
   "line": 94,
   "type": "desc",
   "actor": "Salonika Batrad",
   "b": false
  },
  {
   "line": 95,
   "type": "desc",
   "actor": "Salonika Batrad",
   "b": false
  },
  {
   "line": 96,
   "type": "desc",
   "actor": "Salonika Batrad",
   "b": false
  },
  {
   "line": 97,
   "type": "desc",
   "actor": "Salonika Batrad",
   "b": false
  },
  {
   "line": 98,
   "type": "desc",
   "actor": "Salonika Batrad",
   "b": false
  },
  {
   "line": 99,
   "type": "desc",
   "actor": "Salonika Batrad",
   "b": false
  },
  {
   "line": 100,
   "type": "desc",
   "actor": "Salonika Batrad",
   "b": false
  },
  {
   "line": 101,
   "type": "desc",
   "actor": "Salonika Batrad",
   "b": false
  },
  {
   "line": 102,
   "type": "desc",
   "actor": "Salonika Batrad",
   "b": false
  },
  {
   "line": 103,
   "type": "desc",
   "actor": "Salonika Batrad",
   "b": false
  },
  {
   "line": 104,
   "type": "desc",
   "actor": "Salonika Batrad",
   "b": false
  },
  {
   "line": 105,
   "type": "desc",
   "actor": "Salonika Batrad",
   "b": false
  },
  {
   "line": 107,
   "type": "desc",
   "actor": "Bazil McKenzie",
   "b": false
  },
  {
   "line": 108,
   "type": "desc",
   "actor": "Bazil McKenzie",
   "b": false
  },
  {
   "line": 109,
   "type": "desc",
   "actor": "Bazil McKenzie",
   "b": false
  },
  {
   "line": 110,
   "type": "desc",
   "actor": "Bazil McKenzie",
   "b": false
  },
  {
   "line": 111,
   "type": "desc",
   "actor": "Bazil McKenzie",
   "b": false
  },
  {
   "line": 112,
   "type": "desc",
   "actor": "Bazil McKenzie",
   "b": false
  },
  {
   "line": 113,
   "type": "desc",
   "actor": "Bazil McKenzie",
   "b": false
  },
  {
   "line": 114,
   "type": "desc",
   "actor": "Bazil McKenzie",
   "b": false
  },
  {
   "line": 115,
   "type": "desc",
   "actor": "Bazil McKenzie",
   "b": false
  },
  {
   "line": 116,
   "type": "desc",
   "actor": "Bazil McKenzie",
   "b": false
  },
  {
   "line": 117,
   "type": "desc",
   "actor": "Bazil McKenzie",
   "b": false
  },
  {
   "line": 118,
   "type": "desc",
   "actor": "Bazil McKenzie",
   "b": false
  },
  {
   "line": 119,
   "type": "desc",
   "actor": "Bazil McKenzie",
   "b": false
  },
  {
   "line": 120,
   "type": "desc",
   "actor": "Bazil McKenzie",
   "b": false
  },
  {
   "line": 121,
   "type": "desc",
   "actor": "Bazil McKenzie",
   "b": false
  },
  {
   "line": 122,
   "type": "desc",
   "actor": "Bazil McKenzie",
   "b": false
  },
  {
   "line": 123,
   "type": "desc",
   "actor": "Bazil McKenzie",
   "b": false
  },
  {
   "line": 124,
   "type": "desc",
   "actor": "Bazil McKenzie",
   "b": false
  },
  {
   "line": 125,
   "type": "desc",
   "actor": "Bazil McKenzie",
   "b": false
  },
  {
   "line": 126,
   "type": "desc",
   "actor": "Bazil McKenzie",
   "b": false
  },
  {
   "line": 127,
   "type": "desc",
   "actor": "Bazil McKenzie",
   "b": false
  },
  {
   "line": 128,
   "type": "desc",
   "actor": "Bazil McKenzie",
   "b": false
  },
  {
   "line": 129,
   "type": "desc",
   "actor": "Bazil McKenzie",
   "b": false
  },
  {
   "line": 130,
   "type": "desc",
   "actor": "Bazil McKenzie",
   "b": false
  },
  {
   "line": 131,
   "type": "desc",
   "actor": "Bazil McKenzie",
   "b": false
  },
  {
   "line": 132,
   "type": "desc",
   "actor": "Bazil McKenzie",
   "b": false
  },
  {
   "line": 134,
   "type": "desc",
   "actor": "Arands",
   "b": false
  },
  {
   "line": 135,
   "type": "desc",
   "actor": "Arands",
   "b": false
  },
  {
   "line": 136,
   "type": "desc",
   "actor": "Arands",
   "b": false
  },
  {
   "line": 137,
   "type": "desc",
   "actor": "Arands",
   "b": false
  },
  {
   "line": 138,
   "type": "desc",
   "actor": "Arands",
   "b": false
  },
  {
   "line": 139,
   "type": "desc",
   "actor": "Arands",
   "b": false
  },
  {
   "line": 140,
   "type": "desc",
   "actor": "Arands",
   "b": false
  },
  {
   "line": 141,
   "type": "desc",
   "actor": "Arands",
   "b": false
  },
  {
   "line": 142,
   "type": "desc",
   "actor": "Arands",
   "b": false
  },
  {
   "line": 143,
   "type": "desc",
   "actor": "Arands",
   "b": false
  },
  {
   "line": 144,
   "type": "desc",
   "actor": "Arands",
   "b": false
  },
  {
   "line": 145,
   "type": "desc",
   "actor": "Arands",
   "b": false
  },
  {
   "line": 146,
   "type": "desc",
   "actor": "Arands",
   "b": false
  },
  {
   "line": 147,
   "type": "desc",
   "actor": "Arands",
   "b": false
  },
  {
   "line": 148,
   "type": "desc",
   "actor": "Arands",
   "b": false
  },
  {
   "line": 149,
   "type": "desc",
   "actor": "Arands",
   "b": false
  },
  {
   "line": 150,
   "type": "desc",
   "actor": "Arands",
   "b": false
  },
  {
   "line": 151,
   "type": "desc",
   "actor": "Arands",
   "b": false
  },
  {
   "line": 152,
   "type": "desc",
   "actor": "Arands",
   "b": false
  },
  {
   "line": 153,
   "type": "desc",
   "actor": "Arands",
   "b": false
  },
  {
   "line": 154,
   "type": "desc",
   "actor": "Arands",
   "b": false
  },
  {
   "line": 156,
   "type": "system",
   "actor": "",
   "b": false
  },
  {
   "line": 157,
   "type": "system",
   "actor": "",
   "b": false
  },
  {
   "line": 158,
   "type": "system",
   "actor": "",
   "b": false
  },
  {
   "line": 159,
   "type": "system",
   "actor": "",
   "b": false
  },
  {
   "line": 160,
   "type": "system",
   "actor": "",
   "b": false
  },
  {
   "line": 161,
   "type": "system",
   "actor": "",
   "b": false
  },
  {
   "line": 163,
   "type": "desc",
   "actor": "Dydron",
   "b": false
  },
  {
   "line": 165,
   "type": "desc",
   "actor": "Dydron",
   "b": false
  },
  {
   "line": 166,
   "type": "desc",
   "actor": "Dydron",
   "b": false
  },
  {
   "line": 167,
   "type": "desc",
   "actor": "Dydron",
   "b": false
  },
  {
   "line": 168,
   "type": "desc",
   "actor": "Dydron",
   "b": false
  },
  {
   "line": 169,
   "type": "desc",
   "actor": "Dydron",
   "b": false
  },
  {
   "line": 170,
   "type": "desc",
   "actor": "Dydron",
   "b": false
  },
  {
   "line": 172,
   "type": "system",
   "actor": "",
   "b": false
  },
  {
   "line": 174,
   "type": "room",
   "actor": "",
   "b": false
  },
  {
   "line": 176,
   "type": "room",
   "actor": "",
   "b": false
  },
  {
   "line": 177,
   "type": "room",
   "actor": "",
   "b": false
  },
  {
   "line": 178,
   "type": "room",
   "actor": "",
   "b": false
  },
  {
   "line": 179,
   "type": "room",
   "actor": "",
   "b": false
  },
  {
   "line": 180,
   "type": "room",
   "actor": "",
   "b": false
  },
  {
   "line": 181,
   "type": "room",
   "actor": "",
   "b": false
  },
  {
   "line": 182,
   "type": "room",
   "actor": "",
   "b": false
  },
  {
   "line": 183,
   "type": "room",
   "actor": "",
   "b": false
  },
  {
   "line": 184,
   "type": "room",
   "actor": "",
   "b": false
  },
  {
   "line": 185,
   "type": "room",
   "actor": "",
   "b": false
  },
  {
   "line": 186,
   "type": "room",
   "actor": "",
   "b": false
  },
  {
   "line": 187,
   "type": "room",
   "actor": "",
   "b": false
  },
  {
   "line": 188,
   "type": "room",
   "actor": "",
   "b": false
  },
  {
   "line": 189,
   "type": "room",
   "actor": "",
   "b": false
  },
  {
   "line": 190,
   "type": "room",
   "actor": "",
   "b": false
  },
  {
   "line": 192,
   "type": "system",
   "actor": "",
   "b": false
  },
  {
   "line": 193,
   "type": "system",
   "actor": "",
   "b": false
  },
  {
   "line": 194,
   "type": "system",
   "actor": "",
   "b": false
  },
  {
   "line": 195,
   "type": "system",
   "actor": "",
   "b": false
  },
  {
   "line": 196,
   "type": "system",
   "actor": "",
   "b": false
  },
  {
   "line": 197,
   "type": "system",
   "actor": "",
   "b": false
  },
  {
   "line": 198,
   "type": "system",
   "actor": "",
   "b": false
  },
  {
   "line": 199,
   "type": "system",
   "actor": "",
   "b": false
  },
  {
   "line": 200,
   "type": "system",
   "actor": "",
   "b": false
  },
  {
   "line": 201,
   "type": "system",
   "actor": "",
   "b": false
  },
  {
   "line": 202,
   "type": "system",
   "actor": "",
   "b": false
  },
  {
   "line": 203,
   "type": "system",
   "actor": "",
   "b": false
  },
  {
   "line": 205,
   "type": "pose",
   "actor": "Ernie Pallando",
   "b": false
  },
  {
   "line": 206,
   "type": "pose",
   "actor": "Ernie Pallando",
   "b": false
  },
  {
   "line": 207,
   "type": "pose",
   "actor": "Ernie Pallando",
   "b": false
  },
  {
   "line": 208,
   "type": "pose",
   "actor": "Ernie Pallando",
   "b": false
  },
  {
   "line": 209,
   "type": "pose",
   "actor": "Ernie Pallando",
   "b": false
  },
  {
   "line": 210,
   "type": "pose",
   "actor": "Ernie Pallando",
   "b": false
  },
  {
   "line": 212,
   "type": "scene",
   "actor": "",
   "b": false
  },
  {
   "line": 213,
   "type": "scene",
   "actor": "",
   "b": false
  },
  {
   "line": 214,
   "type": "scene",
   "actor": "",
   "b": false
  },
  {
   "line": 215,
   "type": "scene",
   "actor": "",
   "b": false
  },
  {
   "line": 217,
   "type": "pose",
   "actor": "Nicole Brouillard-Batrad",
   "b": false
  },
  {
   "line": 218,
   "type": "pose",
   "actor": "Nicole Brouillard-Batrad",
   "b": false
  },
  {
   "line": 219,
   "type": "pose",
   "actor": "Nicole Brouillard-Batrad",
   "b": false
  },
  {
   "line": 220,
   "type": "pose",
   "actor": "Nicole Brouillard-Batrad",
   "b": false
  },
  {
   "line": 221,
   "type": "pose",
   "actor": "Nicole Brouillard-Batrad",
   "b": false
  },
  {
   "line": 222,
   "type": "pose",
   "actor": "Nicole Brouillard-Batrad",
   "b": false
  },
  {
   "line": 224,
   "type": "pose",
   "actor": "Loy Marin",
   "b": false
  },
  {
   "line": 225,
   "type": "pose",
   "actor": "Loy Marin",
   "b": false
  },
  {
   "line": 226,
   "type": "pose",
   "actor": "Loy Marin",
   "b": false
  },
  {
   "line": 227,
   "type": "pose",
   "actor": "Loy Marin",
   "b": false
  },
  {
   "line": 228,
   "type": "pose",
   "actor": "Loy Marin",
   "b": false
  },
  {
   "line": 229,
   "type": "pose",
   "actor": "Loy Marin",
   "b": false
  },
  {
   "line": 230,
   "type": "pose",
   "actor": "Loy Marin",
   "b": false
  },
  {
   "line": 231,
   "type": "pose",
   "actor": "Loy Marin",
   "b": false
  },
  {
   "line": 232,
   "type": "pose",
   "actor": "Loy Marin",
   "b": false
  },
  {
   "line": 234,
   "type": "scene",
   "actor": "",
   "b": false
  },
  {
   "line": 235,
   "type": "scene",
   "actor": "",
   "b": false
  },
  {
   "line": 236,
   "type": "scene",
   "actor": "",
   "b": false
  },
  {
   "line": 238,
   "type": "pose",
   "actor": "Salonika Batrad",
   "b": false
  },
  {
   "line": 239,
   "type": "pose",
   "actor": "Salonika Batrad",
   "b": false
  },
  {
   "line": 240,
   "type": "pose",
   "actor": "Salonika Batrad",
   "b": false
  },
  {
   "line": 241,
   "type": "pose",
   "actor": "Salonika Batrad",
   "b": false
  },
  {
   "line": 243,
   "type": "pose",
   "actor": "Arands",
   "b": false
  },
  {
   "line": 244,
   "type": "pose",
   "actor": "Arands",
   "b": false
  },
  {
   "line": 245,
   "type": "pose",
   "actor": "Arands",
   "b": false
  },
  {
   "line": 247,
   "type": "pose",
   "actor": "Bazil McKenzie",
   "b": false
  },
  {
   "line": 248,
   "type": "pose",
   "actor": "Bazil McKenzie",
   "b": false
  },
  {
   "line": 249,
   "type": "pose",
   "actor": "Bazil McKenzie",
   "b": false
  },
  {
   "line": 250,
   "type": "pose",
   "actor": "Bazil McKenzie",
   "b": false
  },
  {
   "line": 251,
   "type": "pose",
   "actor": "Bazil McKenzie",
   "b": false
  },
  {
   "line": 252,
   "type": "pose",
   "actor": "Bazil McKenzie",
   "b": false
  },
  {
   "line": 254,
   "type": "pose",
   "actor": "Ernie Pallando",
   "b": false
  },
  {
   "line": 255,
   "type": "pose",
   "actor": "Ernie Pallando",
   "b": false
  },
  {
   "line": 256,
   "type": "pose",
   "actor": "Ernie Pallando",
   "b": false
  },
  {
   "line": 257,
   "type": "pose",
   "actor": "Ernie Pallando",
   "b": false
  },
  {
   "line": 258,
   "type": "pose",
   "actor": "Ernie Pallando",
   "b": false
  },
  {
   "line": 260,
   "type": "pose",
   "actor": "Dydron",
   "b": false
  },
  {
   "line": 261,
   "type": "pose",
   "actor": "Dydron",
   "b": false
  },
  {
   "line": 262,
   "type": "pose",
   "actor": "Dydron",
   "b": false
  },
  {
   "line": 263,
   "type": "pose",
   "actor": "Dydron",
   "b": false
  },
  {
   "line": 265,
   "type": "pose",
   "actor": "Loy Marin",
   "b": false
  },
  {
   "line": 266,
   "type": "pose",
   "actor": "Loy Marin",
   "b": false
  },
  {
   "line": 267,
   "type": "pose",
   "actor": "Loy Marin",
   "b": false
  },
  {
   "line": 268,
   "type": "pose",
   "actor": "Loy Marin",
   "b": false
  },
  {
   "line": 269,
   "type": "pose",
   "actor": "Loy Marin",
   "b": false
  },
  {
   "line": 270,
   "type": "pose",
   "actor": "Loy Marin",
   "b": false
  },
  {
   "line": 272,
   "type": "pose",
   "actor": "Salonika Batrad",
   "b": false
  },
  {
   "line": 273,
   "type": "pose",
   "actor": "Salonika Batrad",
   "b": false
  },
  {
   "line": 274,
   "type": "pose",
   "actor": "Salonika Batrad",
   "b": false
  },
  {
   "line": 275,
   "type": "pose",
   "actor": "Salonika Batrad",
   "b": false
  },
  {
   "line": 276,
   "type": "pose",
   "actor": "Salonika Batrad",
   "b": false
  },
  {
   "line": 277,
   "type": "pose",
   "actor": "Salonika Batrad",
   "b": false
  },
  {
   "line": 279,
   "type": "pose",
   "actor": "Loy Marin",
   "b": false
  },
  {
   "line": 280,
   "type": "pose",
   "actor": "Loy Marin",
   "b": false
  },
  {
   "line": 281,
   "type": "pose",
   "actor": "Loy Marin",
   "b": false
  },
  {
   "line": 282,
   "type": "pose",
   "actor": "Loy Marin",
   "b": false
  },
  {
   "line": 284,
   "type": "pose",
   "actor": "Ernie Pallando",
   "b": false
  },
  {
   "line": 285,
   "type": "pose",
   "actor": "Ernie Pallando",
   "b": false
  },
  {
   "line": 286,
   "type": "pose",
   "actor": "Ernie Pallando",
   "b": false
  },
  {
   "line": 287,
   "type": "pose",
   "actor": "Ernie Pallando",
   "b": false
  },
  {
   "line": 288,
   "type": "pose",
   "actor": "Ernie Pallando",
   "b": false
  },
  {
   "line": 290,
   "type": "pose",
   "actor": "Nicole Brouillard-Batrad",
   "b": false
  },
  {
   "line": 291,
   "type": "pose",
   "actor": "Nicole Brouillard-Batrad",
   "b": false
  },
  {
   "line": 292,
   "type": "pose",
   "actor": "Nicole Brouillard-Batrad",
   "b": false
  },
  {
   "line": 293,
   "type": "pose",
   "actor": "Nicole Brouillard-Batrad",
   "b": false
  },
  {
   "line": 295,
   "type": "system",
   "actor": "",
   "b": false
  },
  {
   "line": 296,
   "type": "system",
   "actor": "",
   "b": false
  },
  {
   "line": 298,
   "type": "pose",
   "actor": "Ernie Pallando",
   "b": false
  },
  {
   "line": 299,
   "type": "pose",
   "actor": "Ernie Pallando",
   "b": false
  },
  {
   "line": 300,
   "type": "pose",
   "actor": "Ernie Pallando",
   "b": false
  },
  {
   "line": 301,
   "type": "pose",
   "actor": "Ernie Pallando",
   "b": false
  },
  {
   "line": 302,
   "type": "pose",
   "actor": "Ernie Pallando",
   "b": false
  },
  {
   "line": 304,
   "type": "pose",
   "actor": "Bazil McKenzie",
   "b": false
  },
  {
   "line": 305,
   "type": "pose",
   "actor": "Bazil McKenzie",
   "b": false
  },
  {
   "line": 306,
   "type": "pose",
   "actor": "Bazil McKenzie",
   "b": false
  },
  {
   "line": 307,
   "type": "pose",
   "actor": "Bazil McKenzie",
   "b": false
  },
  {
   "line": 308,
   "type": "pose",
   "actor": "Bazil McKenzie",
   "b": false
  },
  {
   "line": 309,
   "type": "pose",
   "actor": "Bazil McKenzie",
   "b": false
  },
  {
   "line": 310,
   "type": "pose",
   "actor": "Bazil McKenzie",
   "b": false
  },
  {
   "line": 312,
   "type": "pose",
   "actor": "Loy Marin",
   "b": false
  },
  {
   "line": 313,
   "type": "pose",
   "actor": "Loy Marin",
   "b": false
  },
  {
   "line": 314,
   "type": "pose",
   "actor": "Loy Marin",
   "b": false
  },
  {
   "line": 315,
   "type": "pose",
   "actor": "Loy Marin",
   "b": false
  },
  {
   "line": 316,
   "type": "pose",
   "actor": "Loy Marin",
   "b": false
  },
  {
   "line": 317,
   "type": "pose",
   "actor": "Loy Marin",
   "b": false
  },
  {
   "line": 319,
   "type": "pose",
   "actor": "Arands",
   "b": false
  },
  {
   "line": 320,
   "type": "pose",
   "actor": "Arands",
   "b": false
  },
  {
   "line": 321,
   "type": "pose",
   "actor": "Arands",
   "b": false
  },
  {
   "line": 322,
   "type": "pose",
   "actor": "Arands",
   "b": false
  },
  {
   "line": 323,
   "type": "pose",
   "actor": "Arands",
   "b": false
  },
  {
   "line": 324,
   "type": "pose",
   "actor": "Arands",
   "b": false
  },
  {
   "line": 325,
   "type": "pose",
   "actor": "Arands",
   "b": false
  },
  {
   "line": 326,
   "type": "pose",
   "actor": "Arands",
   "b": false
  },
  {
   "line": 327,
   "type": "pose",
   "actor": "Arands",
   "b": false
  },
  {
   "line": 328,
   "type": "pose",
   "actor": "Arands",
   "b": false
  },
  {
   "line": 329,
   "type": "pose",
   "actor": "Arands",
   "b": false
  },
  {
   "line": 331,
   "type": "pose",
   "actor": "Dydron",
   "b": false
  },
  {
   "line": 332,
   "type": "pose",
   "actor": "Dydron",
   "b": false
  },
  {
   "line": 333,
   "type": "pose",
   "actor": "Dydron",
   "b": false
  },
  {
   "line": 334,
   "type": "pose",
   "actor": "Dydron",
   "b": false
  },
  {
   "line": 335,
   "type": "pose",
   "actor": "Dydron",
   "b": false
  },
  {
   "line": 337,
   "type": "pose",
   "actor": "Salonika Batrad",
   "b": false
  },
  {
   "line": 338,
   "type": "pose",
   "actor": "Salonika Batrad",
   "b": false
  },
  {
   "line": 339,
   "type": "pose",
   "actor": "Salonika Batrad",
   "b": false
  },
  {
   "line": 340,
   "type": "pose",
   "actor": "Salonika Batrad",
   "b": false
  },
  {
   "line": 341,
   "type": "pose",
   "actor": "Salonika Batrad",
   "b": false
  },
  {
   "line": 342,
   "type": "pose",
   "actor": "Salonika Batrad",
   "b": false
  },
  {
   "line": 343,
   "type": "pose",
   "actor": "Salonika Batrad",
   "b": false
  },
  {
   "line": 344,
   "type": "pose",
   "actor": "Salonika Batrad",
   "b": false
  },
  {
   "line": 346,
   "type": "pose",
   "actor": "Ernie Pallando",
   "b": false
  },
  {
   "line": 347,
   "type": "pose",
   "actor": "Ernie Pallando",
   "b": false
  },
  {
   "line": 348,
   "type": "pose",
   "actor": "Ernie Pallando",
   "b": false
  },
  {
   "line": 349,
   "type": "pose",
   "actor": "Ernie Pallando",
   "b": false
  },
  {
   "line": 351,
   "type": "pose",
   "actor": "Loy Marin",
   "b": false
  },
  {
   "line": 352,
   "type": "pose",
   "actor": "Loy Marin",
   "b": false
  },
  {
   "line": 353,
   "type": "pose",
   "actor": "Loy Marin",
   "b": false
  },
  {
   "line": 354,
   "type": "pose",
   "actor": "Loy Marin",
   "b": false
  },
  {
   "line": 355,
   "type": "pose",
   "actor": "Loy Marin",
   "b": false
  },
  {
   "line": 356,
   "type": "pose",
   "actor": "Loy Marin",
   "b": false
  },
  {
   "line": 357,
   "type": "pose",
   "actor": "Loy Marin",
   "b": false
  },
  {
   "line": 358,
   "type": "pose",
   "actor": "Loy Marin",
   "b": false
  },
  {
   "line": 360,
   "type": "pose",
   "actor": "Nicole Brouillard-Batrad",
   "b": false
  },
  {
   "line": 361,
   "type": "pose",
   "actor": "Nicole Brouillard-Batrad",
   "b": false
  },
  {
   "line": 363,
   "type": "pose",
   "actor": "Arands",
   "b": false
  },
  {
   "line": 364,
   "type": "pose",
   "actor": "Arands",
   "b": false
  },
  {
   "line": 365,
   "type": "pose",
   "actor": "Arands",
   "b": false
  },
  {
   "line": 366,
   "type": "pose",
   "actor": "Arands",
   "b": false
  },
  {
   "line": 367,
   "type": "pose",
   "actor": "Arands",
   "b": false
  },
  {
   "line": 368,
   "type": "pose",
   "actor": "Arands",
   "b": false
  },
  {
   "line": 369,
   "type": "pose",
   "actor": "Arands",
   "b": false
  },
  {
   "line": 370,
   "type": "pose",
   "actor": "Arands",
   "b": false
  },
  {
   "line": 371,
   "type": "pose",
   "actor": "Arands",
   "b": false
  },
  {
   "line": 372,
   "type": "pose",
   "actor": "Arands",
   "b": false
  },
  {
   "line": 374,
   "type": "pose",
   "actor": "Salonika Batrad",
   "b": false
  },
  {
   "line": 375,
   "type": "pose",
   "actor": "Salonika Batrad",
   "b": false
  },
  {
   "line": 376,
   "type": "pose",
   "actor": "Salonika Batrad",
   "b": false
  },
  {
   "line": 377,
   "type": "pose",
   "actor": "Salonika Batrad",
   "b": false
  },
  {
   "line": 378,
   "type": "pose",
   "actor": "Salonika Batrad",
   "b": false
  },
  {
   "line": 379,
   "type": "pose",
   "actor": "Salonika Batrad",
   "b": false
  },
  {
   "line": 380,
   "type": "pose",
   "actor": "Salonika Batrad",
   "b": false
  },
  {
   "line": 381,
   "type": "pose",
   "actor": "Salonika Batrad",
   "b": false
  },
  {
   "line": 383,
   "type": "pose",
   "actor": "Ernie Pallando",
   "b": false
  },
  {
   "line": 384,
   "type": "pose",
   "actor": "Ernie Pallando",
   "b": false
  },
  {
   "line": 385,
   "type": "pose",
   "actor": "Ernie Pallando",
   "b": false
  },
  {
   "line": 386,
   "type": "pose",
   "actor": "Ernie Pallando",
   "b": false
  },
  {
   "line": 387,
   "type": "pose",
   "actor": "Ernie Pallando",
   "b": false
  },
  {
   "line": 389,
   "type": "pose",
   "actor": "Marcus Delvennis",
   "b": false
  },
  {
   "line": 390,
   "type": "pose",
   "actor": "Marcus Delvennis",
   "b": false
  },
  {
   "line": 391,
   "type": "pose",
   "actor": "Marcus Delvennis",
   "b": false
  },
  {
   "line": 392,
   "type": "pose",
   "actor": "Marcus Delvennis",
   "b": false
  },
  {
   "line": 394,
   "type": "pose",
   "actor": "Nicole Brouillard-Batrad",
   "b": false
  },
  {
   "line": 395,
   "type": "pose",
   "actor": "Nicole Brouillard-Batrad",
   "b": false
  },
  {
   "line": 396,
   "type": "pose",
   "actor": "Nicole Brouillard-Batrad",
   "b": false
  },
  {
   "line": 397,
   "type": "pose",
   "actor": "Nicole Brouillard-Batrad",
   "b": false
  },
  {
   "line": 398,
   "type": "pose",
   "actor": "Nicole Brouillard-Batrad",
   "b": false
  },
  {
   "line": 400,
   "type": "pose",
   "actor": "Bazil McKenzie",
   "b": false
  },
  {
   "line": 401,
   "type": "pose",
   "actor": "Bazil McKenzie",
   "b": false
  },
  {
   "line": 402,
   "type": "pose",
   "actor": "Bazil McKenzie",
   "b": false
  },
  {
   "line": 403,
   "type": "pose",
   "actor": "Bazil McKenzie",
   "b": false
  },
  {
   "line": 404,
   "type": "pose",
   "actor": "Bazil McKenzie",
   "b": false
  },
  {
   "line": 405,
   "type": "pose",
   "actor": "Bazil McKenzie",
   "b": false
  },
  {
   "line": 406,
   "type": "pose",
   "actor": "Bazil McKenzie",
   "b": false
  },
  {
   "line": 408,
   "type": "pose",
   "actor": "Loy Marin",
   "b": false
  },
  {
   "line": 409,
   "type": "pose",
   "actor": "Loy Marin",
   "b": false
  },
  {
   "line": 410,
   "type": "pose",
   "actor": "Loy Marin",
   "b": false
  },
  {
   "line": 411,
   "type": "pose",
   "actor": "Loy Marin",
   "b": false
  },
  {
   "line": 412,
   "type": "pose",
   "actor": "Loy Marin",
   "b": false
  },
  {
   "line": 413,
   "type": "pose",
   "actor": "Loy Marin",
   "b": false
  },
  {
   "line": 414,
   "type": "pose",
   "actor": "Loy Marin",
   "b": false
  },
  {
   "line": 415,
   "type": "pose",
   "actor": "Loy Marin",
   "b": false
  },
  {
   "line": 416,
   "type": "pose",
   "actor": "Loy Marin",
   "b": false
  },
  {
   "line": 418,
   "type": "pose",
   "actor": "Arands",
   "b": false
  },
  {
   "line": 419,
   "type": "pose",
   "actor": "Arands",
   "b": false
  },
  {
   "line": 420,
   "type": "pose",
   "actor": "Arands",
   "b": false
  },
  {
   "line": 421,
   "type": "pose",
   "actor": "Arands",
   "b": false
  },
  {
   "line": 422,
   "type": "pose",
   "actor": "Arands",
   "b": false
  },
  {
   "line": 423,
   "type": "pose",
   "actor": "Arands",
   "b": false
  },
  {
   "line": 424,
   "type": "pose",
   "actor": "Arands",
   "b": false
  },
  {
   "line": 425,
   "type": "pose",
   "actor": "Arands",
   "b": false
  },
  {
   "line": 426,
   "type": "pose",
   "actor": "Arands",
   "b": false
  },
  {
   "line": 427,
   "type": "pose",
   "actor": "Arands",
   "b": false
  },
  {
   "line": 429,
   "type": "pose",
   "actor": "Salonika Batrad",
   "b": false
  },
  {
   "line": 430,
   "type": "pose",
   "actor": "Salonika Batrad",
   "b": false
  },
  {
   "line": 431,
   "type": "pose",
   "actor": "Salonika Batrad",
   "b": false
  },
  {
   "line": 432,
   "type": "pose",
   "actor": "Salonika Batrad",
   "b": false
  },
  {
   "line": 433,
   "type": "pose",
   "actor": "Salonika Batrad",
   "b": false
  },
  {
   "line": 434,
   "type": "pose",
   "actor": "Salonika Batrad",
   "b": false
  },
  {
   "line": 435,
   "type": "pose",
   "actor": "Salonika Batrad",
   "b": false
  },
  {
   "line": 436,
   "type": "pose",
   "actor": "Salonika Batrad",
   "b": false
  },
  {
   "line": 438,
   "type": "pose",
   "actor": "Ernie Pallando",
   "b": false
  },
  {
   "line": 439,
   "type": "pose",
   "actor": "Ernie Pallando",
   "b": false
  },
  {
   "line": 440,
   "type": "pose",
   "actor": "Ernie Pallando",
   "b": false
  },
  {
   "line": 441,
   "type": "pose",
   "actor": "Ernie Pallando",
   "b": false
  },
  {
   "line": 442,
   "type": "pose",
   "actor": "Ernie Pallando",
   "b": false
  },
  {
   "line": 443,
   "type": "pose",
   "actor": "Ernie Pallando",
   "b": false
  },
  {
   "line": 445,
   "type": "pose",
   "actor": "Marcus Delvennis",
   "b": false
  },
  {
   "line": 446,
   "type": "pose",
   "actor": "Marcus Delvennis",
   "b": false
  },
  {
   "line": 447,
   "type": "pose",
   "actor": "Marcus Delvennis",
   "b": false
  },
  {
   "line": 448,
   "type": "pose",
   "actor": "Marcus Delvennis",
   "b": false
  },
  {
   "line": 449,
   "type": "pose",
   "actor": "Marcus Delvennis",
   "b": false
  },
  {
   "line": 451,
   "type": "pose",
   "actor": "Bazil McKenzie",
   "b": false
  },
  {
   "line": 452,
   "type": "pose",
   "actor": "Bazil McKenzie",
   "b": false
  },
  {
   "line": 453,
   "type": "pose",
   "actor": "Bazil McKenzie",
   "b": false
  },
  {
   "line": 454,
   "type": "pose",
   "actor": "Bazil McKenzie",
   "b": false
  },
  {
   "line": 455,
   "type": "pose",
   "actor": "Bazil McKenzie",
   "b": false
  },
  {
   "line": 457,
   "type": "pose",
   "actor": "Jonau Diggs",
   "b": false
  },
  {
   "line": 458,
   "type": "pose",
   "actor": "Jonau Diggs",
   "b": false
  },
  {
   "line": 459,
   "type": "pose",
   "actor": "Jonau Diggs",
   "b": false
  },
  {
   "line": 460,
   "type": "pose",
   "actor": "Jonau Diggs",
   "b": false
  },
  {
   "line": 461,
   "type": "pose",
   "actor": "Jonau Diggs",
   "b": false
  },
  {
   "line": 462,
   "type": "pose",
   "actor": "Jonau Diggs",
   "b": false
  },
  {
   "line": 464,
   "type": "pose",
   "actor": "Loy Marin",
   "b": false
  },
  {
   "line": 465,
   "type": "pose",
   "actor": "Loy Marin",
   "b": false
  },
  {
   "line": 466,
   "type": "pose",
   "actor": "Loy Marin",
   "b": false
  },
  {
   "line": 467,
   "type": "pose",
   "actor": "Loy Marin",
   "b": false
  },
  {
   "line": 468,
   "type": "pose",
   "actor": "Loy Marin",
   "b": false
  },
  {
   "line": 469,
   "type": "pose",
   "actor": "Loy Marin",
   "b": false
  },
  {
   "line": 470,
   "type": "pose",
   "actor": "Loy Marin",
   "b": false
  },
  {
   "line": 471,
   "type": "pose",
   "actor": "Loy Marin",
   "b": false
  },
  {
   "line": 472,
   "type": "pose",
   "actor": "Loy Marin",
   "b": false
  },
  {
   "line": 473,
   "type": "pose",
   "actor": "Loy Marin",
   "b": false
  },
  {
   "line": 474,
   "type": "pose",
   "actor": "Loy Marin",
   "b": false
  },
  {
   "line": 476,
   "type": "pose",
   "actor": "Arands",
   "b": false
  },
  {
   "line": 477,
   "type": "pose",
   "actor": "Arands",
   "b": false
  },
  {
   "line": 478,
   "type": "pose",
   "actor": "Arands",
   "b": false
  },
  {
   "line": 479,
   "type": "pose",
   "actor": "Arands",
   "b": false
  },
  {
   "line": 480,
   "type": "pose",
   "actor": "Arands",
   "b": false
  },
  {
   "line": 481,
   "type": "pose",
   "actor": "Arands",
   "b": false
  },
  {
   "line": 482,
   "type": "pose",
   "actor": "Arands",
   "b": false
  },
  {
   "line": 483,
   "type": "pose",
   "actor": "Arands",
   "b": false
  },
  {
   "line": 485,
   "type": "pose",
   "actor": "Nicole Brouillard-Batrad",
   "b": false
  },
  {
   "line": 486,
   "type": "pose",
   "actor": "Nicole Brouillard-Batrad",
   "b": false
  },
  {
   "line": 487,
   "type": "pose",
   "actor": "Nicole Brouillard-Batrad",
   "b": false
  },
  {
   "line": 488,
   "type": "pose",
   "actor": "Nicole Brouillard-Batrad",
   "b": false
  },
  {
   "line": 489,
   "type": "pose",
   "actor": "Nicole Brouillard-Batrad",
   "b": false
  },
  {
   "line": 491,
   "type": "system",
   "actor": "",
   "b": false
  },
  {
   "line": 492,
   "type": "system",
   "actor": "",
   "b": false
  },
  {
   "line": 494,
   "type": "pose",
   "actor": "Dydron",
   "b": false
  },
  {
   "line": 495,
   "type": "pose",
   "actor": "Dydron",
   "b": false
  },
  {
   "line": 496,
   "type": "pose",
   "actor": "Dydron",
   "b": false
  },
  {
   "line": 497,
   "type": "pose",
   "actor": "Dydron",
   "b": false
  },
  {
   "line": 498,
   "type": "pose",
   "actor": "Dydron",
   "b": false
  },
  {
   "line": 500,
   "type": "pose",
   "actor": "Ernie Pallando",
   "b": false
  },
  {
   "line": 501,
   "type": "pose",
   "actor": "Ernie Pallando",
   "b": false
  },
  {
   "line": 502,
   "type": "pose",
   "actor": "Ernie Pallando",
   "b": false
  },
  {
   "line": 503,
   "type": "pose",
   "actor": "Ernie Pallando",
   "b": false
  },
  {
   "line": 505,
   "type": "system",
   "actor": "",
   "b": false
  },
  {
   "line": 506,
   "type": "system",
   "actor": "",
   "b": false
  },
  {
   "line": 508,
   "type": "pose",
   "actor": "Marcus Delvennis",
   "b": false
  },
  {
   "line": 509,
   "type": "pose",
   "actor": "Marcus Delvennis",
   "b": false
  },
  {
   "line": 510,
   "type": "pose",
   "actor": "Marcus Delvennis",
   "b": false
  },
  {
   "line": 511,
   "type": "pose",
   "actor": "Marcus Delvennis",
   "b": false
  },
  {
   "line": 512,
   "type": "pose",
   "actor": "Marcus Delvennis",
   "b": false
  },
  {
   "line": 514,
   "type": "pose",
   "actor": "Salonika Batrad",
   "b": false
  },
  {
   "line": 515,
   "type": "pose",
   "actor": "Salonika Batrad",
   "b": false
  },
  {
   "line": 516,
   "type": "pose",
   "actor": "Salonika Batrad",
   "b": false
  },
  {
   "line": 517,
   "type": "pose",
   "actor": "Salonika Batrad",
   "b": false
  },
  {
   "line": 518,
   "type": "pose",
   "actor": "Salonika Batrad",
   "b": false
  },
  {
   "line": 519,
   "type": "pose",
   "actor": "Salonika Batrad",
   "b": false
  },
  {
   "line": 520,
   "type": "pose",
   "actor": "Salonika Batrad",
   "b": false
  },
  {
   "line": 522,
   "type": "pose",
   "actor": "Bazil McKenzie",
   "b": false
  },
  {
   "line": 523,
   "type": "pose",
   "actor": "Bazil McKenzie",
   "b": false
  },
  {
   "line": 524,
   "type": "pose",
   "actor": "Bazil McKenzie",
   "b": false
  },
  {
   "line": 525,
   "type": "pose",
   "actor": "Bazil McKenzie",
   "b": false
  },
  {
   "line": 527,
   "type": "pose",
   "actor": "Jonau Diggs",
   "b": false
  },
  {
   "line": 528,
   "type": "pose",
   "actor": "Jonau Diggs",
   "b": false
  },
  {
   "line": 529,
   "type": "pose",
   "actor": "Jonau Diggs",
   "b": false
  },
  {
   "line": 530,
   "type": "pose",
   "actor": "Jonau Diggs",
   "b": false
  },
  {
   "line": 531,
   "type": "pose",
   "actor": "Jonau Diggs",
   "b": false
  },
  {
   "line": 532,
   "type": "pose",
   "actor": "Jonau Diggs",
   "b": false
  },
  {
   "line": 534,
   "type": "pose",
   "actor": "Loy Marin",
   "b": false
  },
  {
   "line": 535,
   "type": "pose",
   "actor": "Loy Marin",
   "b": false
  },
  {
   "line": 536,
   "type": "pose",
   "actor": "Loy Marin",
   "b": false
  },
  {
   "line": 537,
   "type": "pose",
   "actor": "Loy Marin",
   "b": false
  },
  {
   "line": 538,
   "type": "pose",
   "actor": "Loy Marin",
   "b": false
  },
  {
   "line": 539,
   "type": "pose",
   "actor": "Loy Marin",
   "b": false
  },
  {
   "line": 540,
   "type": "pose",
   "actor": "Loy Marin",
   "b": false
  },
  {
   "line": 541,
   "type": "pose",
   "actor": "Loy Marin",
   "b": false
  },
  {
   "line": 542,
   "type": "pose",
   "actor": "Loy Marin",
   "b": false
  },
  {
   "line": 543,
   "type": "pose",
   "actor": "Loy Marin",
   "b": false
  },
  {
   "line": 544,
   "type": "pose",
   "actor": "Loy Marin",
   "b": false
  },
  {
   "line": 546,
   "type": "pose",
   "actor": "Benjawa",
   "b": false
  },
  {
   "line": 547,
   "type": "pose",
   "actor": "Benjawa",
   "b": false
  },
  {
   "line": 548,
   "type": "pose",
   "actor": "Benjawa",
   "b": false
  },
  {
   "line": 549,
   "type": "pose",
   "actor": "Benjawa",
   "b": false
  },
  {
   "line": 550,
   "type": "pose",
   "actor": "Benjawa",
   "b": false
  },
  {
   "line": 551,
   "type": "pose",
   "actor": "Benjawa",
   "b": false
  },
  {
   "line": 552,
   "type": "pose",
   "actor": "Benjawa",
   "b": false
  },
  {
   "line": 553,
   "type": "pose",
   "actor": "Benjawa",
   "b": false
  },
  {
   "line": 554,
   "type": "pose",
   "actor": "Benjawa",
   "b": false
  },
  {
   "line": 555,
   "type": "pose",
   "actor": "Benjawa",
   "b": false
  },
  {
   "line": 556,
   "type": "pose",
   "actor": "Benjawa",
   "b": false
  },
  {
   "line": 557,
   "type": "pose",
   "actor": "Benjawa",
   "b": false
  },
  {
   "line": 558,
   "type": "pose",
   "actor": "Benjawa",
   "b": false
  },
  {
   "line": 559,
   "type": "pose",
   "actor": "Benjawa",
   "b": false
  },
  {
   "line": 561,
   "type": "system",
   "actor": "",
   "b": false
  },
  {
   "line": 562,
   "type": "system",
   "actor": "",
   "b": false
  },
  {
   "line": 564,
   "type": "scene",
   "actor": "",
   "b": false
  },
  {
   "line": 565,
   "type": "scene",
   "actor": "",
   "b": false
  },
  {
   "line": 566,
   "type": "scene",
   "actor": "",
   "b": false
  },
  {
   "line": 567,
   "type": "scene",
   "actor": "",
   "b": false
  },
  {
   "line": 568,
   "type": "scene",
   "actor": "",
   "b": false
  },
  {
   "line": 569,
   "type": "scene",
   "actor": "",
   "b": false
  },
  {
   "line": 571,
   "type": "pose",
   "actor": "Arands",
   "b": false
  },
  {
   "line": 572,
   "type": "pose",
   "actor": "Arands",
   "b": false
  },
  {
   "line": 573,
   "type": "pose",
   "actor": "Arands",
   "b": false
  },
  {
   "line": 574,
   "type": "pose",
   "actor": "Arands",
   "b": false
  },
  {
   "line": 575,
   "type": "pose",
   "actor": "Arands",
   "b": false
  },
  {
   "line": 576,
   "type": "pose",
   "actor": "Arands",
   "b": false
  },
  {
   "line": 577,
   "type": "pose",
   "actor": "Arands",
   "b": false
  },
  {
   "line": 578,
   "type": "pose",
   "actor": "Arands",
   "b": false
  },
  {
   "line": 579,
   "type": "pose",
   "actor": "Arands",
   "b": false
  },
  {
   "line": 580,
   "type": "pose",
   "actor": "Arands",
   "b": false
  },
  {
   "line": 581,
   "type": "pose",
   "actor": "Arands",
   "b": false
  },
  {
   "line": 582,
   "type": "pose",
   "actor": "Arands",
   "b": false
  },
  {
   "line": 583,
   "type": "pose",
   "actor": "Arands",
   "b": false
  },
  {
   "line": 584,
   "type": "pose",
   "actor": "Arands",
   "b": false
  },
  {
   "line": 586,
   "type": "pose",
   "actor": "Rachet",
   "b": false
  },
  {
   "line": 587,
   "type": "pose",
   "actor": "Rachet",
   "b": false
  },
  {
   "line": 588,
   "type": "pose",
   "actor": "Rachet",
   "b": false
  },
  {
   "line": 589,
   "type": "pose",
   "actor": "Rachet",
   "b": false
  },
  {
   "line": 590,
   "type": "pose",
   "actor": "Rachet",
   "b": false
  },
  {
   "line": 591,
   "type": "pose",
   "actor": "Rachet",
   "b": false
  },
  {
   "line": 592,
   "type": "pose",
   "actor": "Rachet",
   "b": false
  },
  {
   "line": 594,
   "type": "pose",
   "actor": "Jonau Diggs",
   "b": false
  },
  {
   "line": 595,
   "type": "pose",
   "actor": "Jonau Diggs",
   "b": false
  },
  {
   "line": 596,
   "type": "pose",
   "actor": "Jonau Diggs",
   "b": false
  },
  {
   "line": 597,
   "type": "pose",
   "actor": "Jonau Diggs",
   "b": false
  },
  {
   "line": 598,
   "type": "pose",
   "actor": "Jonau Diggs",
   "b": false
  },
  {
   "line": 600,
   "type": "pose",
   "actor": "Salonika Batrad",
   "b": false
  },
  {
   "line": 601,
   "type": "pose",
   "actor": "Salonika Batrad",
   "b": false
  },
  {
   "line": 602,
   "type": "pose",
   "actor": "Salonika Batrad",
   "b": false
  },
  {
   "line": 603,
   "type": "pose",
   "actor": "Salonika Batrad",
   "b": false
  },
  {
   "line": 604,
   "type": "pose",
   "actor": "Salonika Batrad",
   "b": false
  },
  {
   "line": 606,
   "type": "pose",
   "actor": "Nicole Brouillard-Batrad",
   "b": false
  },
  {
   "line": 607,
   "type": "pose",
   "actor": "Nicole Brouillard-Batrad",
   "b": false
  },
  {
   "line": 609,
   "type": "pose",
   "actor": "Marcus Delvennis",
   "b": false
  },
  {
   "line": 610,
   "type": "pose",
   "actor": "Marcus Delvennis",
   "b": false
  },
  {
   "line": 611,
   "type": "pose",
   "actor": "Marcus Delvennis",
   "b": false
  },
  {
   "line": 612,
   "type": "pose",
   "actor": "Marcus Delvennis",
   "b": false
  },
  {
   "line": 613,
   "type": "pose",
   "actor": "Marcus Delvennis",
   "b": false
  },
  {
   "line": 615,
   "type": "pose",
   "actor": "Loy Marin",
   "b": false
  },
  {
   "line": 616,
   "type": "pose",
   "actor": "Loy Marin",
   "b": false
  },
  {
   "line": 617,
   "type": "pose",
   "actor": "Loy Marin",
   "b": false
  },
  {
   "line": 618,
   "type": "pose",
   "actor": "Loy Marin",
   "b": false
  },
  {
   "line": 619,
   "type": "pose",
   "actor": "Loy Marin",
   "b": false
  },
  {
   "line": 620,
   "type": "pose",
   "actor": "Loy Marin",
   "b": false
  },
  {
   "line": 621,
   "type": "pose",
   "actor": "Loy Marin",
   "b": false
  },
  {
   "line": 622,
   "type": "pose",
   "actor": "Loy Marin",
   "b": false
  },
  {
   "line": 623,
   "type": "pose",
   "actor": "Loy Marin",
   "b": false
  },
  {
   "line": 624,
   "type": "pose",
   "actor": "Loy Marin",
   "b": false
  },
  {
   "line": 625,
   "type": "pose",
   "actor": "Loy Marin",
   "b": false
  },
  {
   "line": 627,
   "type": "pose",
   "actor": "Benjawa",
   "b": false
  },
  {
   "line": 628,
   "type": "pose",
   "actor": "Benjawa",
   "b": false
  },
  {
   "line": 629,
   "type": "pose",
   "actor": "Benjawa",
   "b": false
  },
  {
   "line": 630,
   "type": "pose",
   "actor": "Benjawa",
   "b": false
  },
  {
   "line": 631,
   "type": "pose",
   "actor": "Benjawa",
   "b": false
  },
  {
   "line": 632,
   "type": "pose",
   "actor": "Benjawa",
   "b": false
  },
  {
   "line": 633,
   "type": "pose",
   "actor": "Benjawa",
   "b": false
  },
  {
   "line": 634,
   "type": "pose",
   "actor": "Benjawa",
   "b": false
  },
  {
   "line": 635,
   "type": "pose",
   "actor": "Benjawa",
   "b": false
  },
  {
   "line": 637,
   "type": "pose",
   "actor": "Arands",
   "b": false
  },
  {
   "line": 638,
   "type": "pose",
   "actor": "Arands",
   "b": false
  },
  {
   "line": 639,
   "type": "pose",
   "actor": "Arands",
   "b": false
  },
  {
   "line": 640,
   "type": "pose",
   "actor": "Arands",
   "b": false
  },
  {
   "line": 641,
   "type": "pose",
   "actor": "Arands",
   "b": false
  },
  {
   "line": 642,
   "type": "pose",
   "actor": "Arands",
   "b": false
  },
  {
   "line": 643,
   "type": "pose",
   "actor": "Arands",
   "b": false
  },
  {
   "line": 644,
   "type": "pose",
   "actor": "Arands",
   "b": false
  },
  {
   "line": 646,
   "type": "pose",
   "actor": "Salonika Batrad",
   "b": false
  },
  {
   "line": 647,
   "type": "pose",
   "actor": "Salonika Batrad",
   "b": false
  },
  {
   "line": 648,
   "type": "pose",
   "actor": "Salonika Batrad",
   "b": false
  },
  {
   "line": 649,
   "type": "pose",
   "actor": "Salonika Batrad",
   "b": false
  },
  {
   "line": 651,
   "type": "pose",
   "actor": "Dydron",
   "b": false
  },
  {
   "line": 652,
   "type": "pose",
   "actor": "Dydron",
   "b": false
  },
  {
   "line": 653,
   "type": "pose",
   "actor": "Dydron",
   "b": false
  },
  {
   "line": 654,
   "type": "pose",
   "actor": "Dydron",
   "b": false
  },
  {
   "line": 656,
   "type": "system",
   "actor": "",
   "b": false
  },
  {
   "line": 657,
   "type": "system",
   "actor": "",
   "b": false
  },
  {
   "line": 659,
   "type": "pose",
   "actor": "Loy Marin",
   "b": false
  },
  {
   "line": 660,
   "type": "pose",
   "actor": "Loy Marin",
   "b": false
  },
  {
   "line": 661,
   "type": "pose",
   "actor": "Loy Marin",
   "b": false
  },
  {
   "line": 662,
   "type": "pose",
   "actor": "Loy Marin",
   "b": false
  },
  {
   "line": 663,
   "type": "pose",
   "actor": "Loy Marin",
   "b": false
  },
  {
   "line": 664,
   "type": "pose",
   "actor": "Loy Marin",
   "b": false
  },
  {
   "line": 665,
   "type": "pose",
   "actor": "Loy Marin",
   "b": false
  },
  {
   "line": 666,
   "type": "pose",
   "actor": "Loy Marin",
   "b": false
  },
  {
   "line": 667,
   "type": "pose",
   "actor": "Loy Marin",
   "b": false
  },
  {
   "line": 668,
   "type": "pose",
   "actor": "Loy Marin",
   "b": false
  },
  {
   "line": 669,
   "type": "pose",
   "actor": "Loy Marin",
   "b": false
  },
  {
   "line": 671,
   "type": "pose",
   "actor": "Marcus Delvennis",
   "b": false
  },
  {
   "line": 672,
   "type": "pose",
   "actor": "Marcus Delvennis",
   "b": false
  },
  {
   "line": 673,
   "type": "pose",
   "actor": "Marcus Delvennis",
   "b": false
  },
  {
   "line": 674,
   "type": "pose",
   "actor": "Marcus Delvennis",
   "b": false
  },
  {
   "line": 676,
   "type": "scene",
   "actor": "",
   "b": false
  },
  {
   "line": 677,
   "type": "scene",
   "actor": "",
   "b": false
  },
  {
   "line": 679,
   "type": "pose",
   "actor": "Bazil McKenzie",
   "b": false
  },
  {
   "line": 680,
   "type": "pose",
   "actor": "Bazil McKenzie",
   "b": false
  },
  {
   "line": 681,
   "type": "pose",
   "actor": "Bazil McKenzie",
   "b": false
  },
  {
   "line": 682,
   "type": "pose",
   "actor": "Bazil McKenzie",
   "b": false
  },
  {
   "line": 684,
   "type": "system",
   "actor": "",
   "b": false
  },
  {
   "line": 686,
   "type": "pose",
   "actor": "Marcus Delvennis",
   "b": false
  },
  {
   "line": 687,
   "type": "pose",
   "actor": "Marcus Delvennis",
   "b": false
  },
  {
   "line": 689,
   "type": "pose",
   "actor": "Benjawa",
   "b": false
  },
  {
   "line": 690,
   "type": "pose",
   "actor": "Benjawa",
   "b": false
  },
  {
   "line": 691,
   "type": "pose",
   "actor": "Benjawa",
   "b": false
  },
  {
   "line": 692,
   "type": "pose",
   "actor": "Benjawa",
   "b": false
  },
  {
   "line": 694,
   "type": "system",
   "actor": "",
   "b": false
  },
  {
   "line": 695,
   "type": "system",
   "actor": "",
   "b": false
  },
  {
   "line": 697,
   "type": "pose",
   "actor": "Loy Marin",
   "b": false
  },
  {
   "line": 698,
   "type": "pose",
   "actor": "Loy Marin",
   "b": false
  },
  {
   "line": 699,
   "type": "pose",
   "actor": "Loy Marin",
   "b": false
  },
  {
   "line": 700,
   "type": "pose",
   "actor": "Loy Marin",
   "b": false
  },
  {
   "line": 701,
   "type": "pose",
   "actor": "Loy Marin",
   "b": false
  },
  {
   "line": 702,
   "type": "pose",
   "actor": "Loy Marin",
   "b": false
  },
  {
   "line": 703,
   "type": "pose",
   "actor": "Loy Marin",
   "b": false
  },
  {
   "line": 704,
   "type": "pose",
   "actor": "Loy Marin",
   "b": false
  },
  {
   "line": 706,
   "type": "pose",
   "actor": "Bazil McKenzie",
   "b": false
  },
  {
   "line": 707,
   "type": "pose",
   "actor": "Bazil McKenzie",
   "b": false
  },
  {
   "line": 708,
   "type": "pose",
   "actor": "Bazil McKenzie",
   "b": false
  },
  {
   "line": 709,
   "type": "pose",
   "actor": "Bazil McKenzie",
   "b": false
  },
  {
   "line": 710,
   "type": "pose",
   "actor": "Bazil McKenzie",
   "b": false
  },
  {
   "line": 711,
   "type": "pose",
   "actor": "Bazil McKenzie",
   "b": false
  },
  {
   "line": 713,
   "type": "pose",
   "actor": "Benjawa",
   "b": false
  },
  {
   "line": 714,
   "type": "pose",
   "actor": "Benjawa",
   "b": false
  },
  {
   "line": 715,
   "type": "pose",
   "actor": "Benjawa",
   "b": false
  },
  {
   "line": 716,
   "type": "pose",
   "actor": "Benjawa",
   "b": false
  },
  {
   "line": 717,
   "type": "pose",
   "actor": "Benjawa",
   "b": false
  },
  {
   "line": 718,
   "type": "pose",
   "actor": "Benjawa",
   "b": false
  },
  {
   "line": 719,
   "type": "pose",
   "actor": "Benjawa",
   "b": false
  },
  {
   "line": 721,
   "type": "pose",
   "actor": "Marcus Delvennis",
   "b": false
  },
  {
   "line": 722,
   "type": "pose",
   "actor": "Marcus Delvennis",
   "b": false
  },
  {
   "line": 723,
   "type": "pose",
   "actor": "Marcus Delvennis",
   "b": false
  },
  {
   "line": 725,
   "type": "pose",
   "actor": "Loy Marin",
   "b": false
  },
  {
   "line": 726,
   "type": "pose",
   "actor": "Loy Marin",
   "b": false
  },
  {
   "line": 727,
   "type": "pose",
   "actor": "Loy Marin",
   "b": false
  },
  {
   "line": 728,
   "type": "pose",
   "actor": "Loy Marin",
   "b": false
  },
  {
   "line": 729,
   "type": "pose",
   "actor": "Loy Marin",
   "b": false
  },
  {
   "line": 730,
   "type": "pose",
   "actor": "Loy Marin",
   "b": false
  },
  {
   "line": 731,
   "type": "pose",
   "actor": "Loy Marin",
   "b": false
  },
  {
   "line": 732,
   "type": "pose",
   "actor": "Loy Marin",
   "b": false
  },
  {
   "line": 733,
   "type": "pose",
   "actor": "Loy Marin",
   "b": false
  },
  {
   "line": 734,
   "type": "pose",
   "actor": "Loy Marin",
   "b": false
  },
  {
   "line": 736,
   "type": "system",
   "actor": "",
   "b": false
  },
  {
   "line": 737,
   "type": "system",
   "actor": "",
   "b": false
  },
  {
   "line": 739,
   "type": "pose",
   "actor": "Bazil McKenzie",
   "b": false
  },
  {
   "line": 740,
   "type": "pose",
   "actor": "Bazil McKenzie",
   "b": false
  },
  {
   "line": 741,
   "type": "pose",
   "actor": "Bazil McKenzie",
   "b": false
  },
  {
   "line": 742,
   "type": "pose",
   "actor": "Bazil McKenzie",
   "b": false
  },
  {
   "line": 743,
   "type": "pose",
   "actor": "Bazil McKenzie",
   "b": false
  },
  {
   "line": 744,
   "type": "pose",
   "actor": "Bazil McKenzie",
   "b": false
  },
  {
   "line": 746,
   "type": "pose",
   "actor": "Benjawa",
   "b": false
  },
  {
   "line": 747,
   "type": "pose",
   "actor": "Benjawa",
   "b": false
  },
  {
   "line": 748,
   "type": "pose",
   "actor": "Benjawa",
   "b": false
  },
  {
   "line": 749,
   "type": "pose",
   "actor": "Benjawa",
   "b": false
  },
  {
   "line": 750,
   "type": "pose",
   "actor": "Benjawa",
   "b": false
  },
  {
   "line": 751,
   "type": "pose",
   "actor": "Benjawa",
   "b": false
  },
  {
   "line": 752,
   "type": "pose",
   "actor": "Benjawa",
   "b": false
  },
  {
   "line": 753,
   "type": "pose",
   "actor": "Benjawa",
   "b": false
  },
  {
   "line": 755,
   "type": "pose",
   "actor": "Loy Marin",
   "b": false
  },
  {
   "line": 756,
   "type": "pose",
   "actor": "Loy Marin",
   "b": false
  },
  {
   "line": 757,
   "type": "pose",
   "actor": "Loy Marin",
   "b": false
  },
  {
   "line": 758,
   "type": "pose",
   "actor": "Loy Marin",
   "b": false
  },
  {
   "line": 760,
   "type": "pose",
   "actor": "Marcus Delvennis",
   "b": false
  },
  {
   "line": 761,
   "type": "pose",
   "actor": "Marcus Delvennis",
   "b": false
  },
  {
   "line": 763,
   "type": "pose",
   "actor": "Benjawa",
   "b": false
  },
  {
   "line": 764,
   "type": "pose",
   "actor": "Benjawa",
   "b": false
  },
  {
   "line": 766,
   "type": "pose",
   "actor": "Bazil McKenzie",
   "b": false
  },
  {
   "line": 767,
   "type": "pose",
   "actor": "Bazil McKenzie",
   "b": false
  },
  {
   "line": 769,
   "type": "system",
   "actor": "",
   "b": false
  },
  {
   "line": 771,
   "type": "system",
   "actor": "",
   "b": false
  }
 ]
}