{
  "name": "RPlog_Harsh_Realities",
  "title": "A Sleepless Night and an Unwanted Answer",
  "summary": "In the Academy Library, the haggard archaeologist Paul Nighman has buried himself in Mandalorian language drills for two sleepless days when his childhood mentor, the Mon Calamari Dr. Molari Canto, gently confronts him about using study to avoid his feelings. After a tense, guilt-laden exchange, Paul leaves to walk the shoreline and wrestle with his confusion over Shenner, a young woman who has confessed her love for him. Turning his researcher's mind on the problem, he admits he cares for her and is even attracted to her, but concludes she is too young and fragile and that he is the wrong man to return her affection. Unsatisfied by the correct answer, Paul resolves that he cannot end things from a distance and must return to face Shenner directly. The log is an introspective solo character piece centered entirely on Paul's reckoning with himself.",
  "rows": [
    {"line": 17, "type": "room", "actor": "", "b": false},
    {"line": 18, "type": "room", "actor": "", "b": false},
    {"line": 20, "type": "scene", "actor": "", "b": false},
    {"line": 22, "type": "pose", "actor": "Paul Nighman", "b": false},
    {"line": 24, "type": "pose", "actor": "Molari Canto", "b": false},
    {"line": 26, "type": "pose", "actor": "Molari Canto", "b": true},
    {"line": 28, "type": "pose", "actor": "Paul Nighman", "b": false},
    {"line": 30, "type": "pose", "actor": "Molari Canto", "b": false},
    {"line": 32, "type": "pose", "actor": "Paul Nighman", "b": false},
    {"line": 34, "type": "pose", "actor": "Molari Canto", "b": false},
    {"line": 36, "type": "pose", "actor": "Paul Nighman", "b": false},
    {"line": 38, "type": "pose", "actor": "Molari Canto", "b": false},
    {"line": 40, "type": "pose", "actor": "Molari Canto", "b": true},
    {"line": 42, "type": "pose", "actor": "Paul Nighman", "b": false},
    {"line": 44, "type": "pose", "actor": "Molari Canto", "b": false},
    {"line": 46, "type": "pose", "actor": "Paul Nighman", "b": false},
    {"line": 48, "type": "pose", "actor": "Paul Nighman", "b": true},
    {"line": 50, "type": "pose", "actor": "Paul Nighman", "b": true},
    {"line": 52, "type": "pose", "actor": "Paul Nighman", "b": true},
    {"line": 54, "type": "pose", "actor": "Paul Nighman", "b": true},
    {"line": 56, "type": "pose", "actor": "Paul Nighman", "b": true},
    {"line": 58, "type": "pose", "actor": "Paul Nighman", "b": true},
    {"line": 60, "type": "pose", "actor": "Paul Nighman", "b": true},
    {"line": 62, "type": "pose", "actor": "Paul Nighman", "b": true},
    {"line": 64, "type": "pose", "actor": "Paul Nighman", "b": true},
    {"line": 66, "type": "pose", "actor": "Paul Nighman", "b": true},
    {"line": 68, "type": "system", "actor": "", "b": false}
  ]
}
